{
  "schema": 1,
  "lastSHA": "eb19359",
  "branch": "go-public",
  "lastRun": { "kind": "map", "at": "2026-06-21T13:34:20Z", "ok": true },
  "findingCounter": 14,
  "files": {
    "cmd/bot/main.go":            { "hash": "d11732dbd4f9608ab041fb7e204a79ab246f11cf", "coverage": "full", "reason": null, "lines": 89,  "lastReadSHA": "eb19359", "passId": 1 },
    "internal/bot/bot.go":        { "hash": "950b768896377d2262c960fb37b05d60f4e954e6", "coverage": "full", "reason": null, "lines": 195, "lastReadSHA": "eb19359", "passId": 1 },
    "internal/bot/userdata.go":   { "hash": "debdabce9144630c9f0d5d0316ded3735b2add49", "coverage": "full", "reason": null, "lines": 92,  "lastReadSHA": "eb19359", "passId": 1 },
    "internal/bot/prep.go":       { "hash": "e789b96198ec447b1554cd982d41e1763ac91e5b", "coverage": "full", "reason": null, "lines": 155, "lastReadSHA": "eb19359", "passId": 1 },
    "internal/bot/aiqueue.go":    { "hash": "2321bc77c80c01e60abf1807c5cf1b10c16305ec", "coverage": "full", "reason": null, "lines": 37,  "lastReadSHA": "eb19359", "passId": 2 },
    "internal/bot/aichat.go":     { "hash": "08c3d1124f04c03716846cd0f43f35cc0a457284", "coverage": "full", "reason": null, "lines": 47,  "lastReadSHA": "eb19359", "passId": 2 },
    "internal/bot/errreport.go":  { "hash": "51673e51fc6430e64aba85dcf572b82d9fdc16ed", "coverage": "full", "reason": null, "lines": 144, "lastReadSHA": "eb19359", "passId": 2 },
    "internal/bot/jobs.go":       { "hash": "d8b288a205529514d615b0dddda14da53f64b480", "coverage": "full", "reason": null, "lines": 61,  "lastReadSHA": "eb19359", "passId": 2 },
    "internal/bot/background.go": { "hash": "81e03632d0a542b510a2291ad8ce15c599887b07", "coverage": "full", "reason": null, "lines": 291, "lastReadSHA": "eb19359", "passId": 2 },
    "internal/dynset/dynset.go":  { "hash": "45f0db057769d122fceae552e28c079e02c76c5d", "coverage": "full", "reason": null, "lines": 111, "lastReadSHA": "eb19359", "passId": 2 },
    "internal/db/db.go":          { "hash": "ff8f3f7964347fb32b6d5e0a93a6af52eec17c08", "coverage": "full", "reason": null, "lines": 168, "lastReadSHA": "eb19359", "passId": 3 },
    "internal/db/users.go":       { "hash": "990246f53922a5ec43910b61f78d3c0ee506b31c", "coverage": "full", "reason": null, "lines": 158, "lastReadSHA": "eb19359", "passId": 3 },
    "internal/db/cids.go":        { "hash": "b3e7c0702090e53e85cc3655df4f3c4d03d0602b", "coverage": "full", "reason": null, "lines": 72,  "lastReadSHA": "eb19359", "passId": 3 },
    "internal/db/blocks.go":      { "hash": "96f9028c593138a08d0952f8d4b1ef635f1e87c9", "coverage": "full", "reason": null, "lines": 59,  "lastReadSHA": "eb19359", "passId": 3 },
    "internal/db/reports.go":     { "hash": "b397f7db2fd158e8f5cc637a49b07673d013bf13", "coverage": "full", "reason": null, "lines": 59,  "lastReadSHA": "eb19359", "passId": 3 },
    "internal/bot/sendmsg.go":    { "hash": "d33c9401ba4ab9bd31cd8c989095d021e9b3f4d4", "coverage": "full", "reason": null, "lines": 459, "lastReadSHA": "eb19359", "passId": 4 },
    "internal/bot/start.go":      { "hash": "c43478ea980e6eb1410c1769f56e83168e7b6b03", "coverage": "full", "reason": null, "lines": 163, "lastReadSHA": "eb19359", "passId": 4 },
    "internal/bot/inituser.go":   { "hash": "2b2660e062e07ff4286628960f6a32966a29cc7e", "coverage": "full", "reason": null, "lines": 63,  "lastReadSHA": "eb19359", "passId": 4 },
    "internal/bot/getuser.go":    { "hash": "c39278e8a96109189616de6affce1bc046fa3f20", "coverage": "full", "reason": null, "lines": 61,  "lastReadSHA": "eb19359", "passId": 4 },
    "internal/bot/helpers.go":    { "hash": "cde6b83e4b08a205a2217aed213439c9a63878eb", "coverage": "full", "reason": null, "lines": 111, "lastReadSHA": "eb19359", "passId": 5 },
    "internal/bot/handlers.go":   { "hash": "c244a3e49225e0d28e64b82c56343bf0ce86ce36", "coverage": "full", "reason": null, "lines": 280, "lastReadSHA": "eb19359", "passId": 5 },
    "internal/bot/callbacks.go":  { "hash": "eeea50666e31bde47ad708281de820ac5b24174a", "coverage": "full", "reason": null, "lines": 559, "lastReadSHA": "eb19359", "passId": 5 },
    "internal/bot/media.go":      { "hash": "125e396867b2127b2c98a153841ccadc10dc8fc3", "coverage": "full", "reason": null, "lines": 238, "lastReadSHA": "eb19359", "passId": 6 },
    "internal/bot/cidchid.go":    { "hash": "c6f8032daf16a0c69d8c0a96171c98ba585933c4", "coverage": "full", "reason": null, "lines": 60,  "lastReadSHA": "eb19359", "passId": 6 },
    "internal/bot/targetsend.go": { "hash": "3480460afa46f8a06e33632c2abfada2ead40a6d", "coverage": "full", "reason": null, "lines": 60,  "lastReadSHA": "eb19359", "passId": 6 },
    "internal/bot/tgerr.go":      { "hash": "b7634d13f0a284dda053d5d1b4addef136143597", "coverage": "full", "reason": null, "lines": 84,  "lastReadSHA": "eb19359", "passId": 6 },
    "internal/bot/othermsgs.go":  { "hash": "9489e2897b86cd0362f5de08c0b60be177eb040c", "coverage": "full", "reason": null, "lines": 39,  "lastReadSHA": "eb19359", "passId": 6 },
    "internal/bot/settings.go":   { "hash": "35c63bbc75ce2382dfdc2083bfcb295c4e6e4534", "coverage": "full", "reason": null, "lines": 444, "lastReadSHA": "eb19359", "passId": 7 },
    "internal/bot/mylinks.go":    { "hash": "48eeb5cacc0083abb3fa29ebb1f7cbbac447905d", "coverage": "full", "reason": null, "lines": 388, "lastReadSHA": "eb19359", "passId": 7 },
    "internal/bot/autoreply.go":  { "hash": "c6f3e8fc61e278fb57b03bebf730fac678c3c459", "coverage": "full", "reason": null, "lines": 296, "lastReadSHA": "eb19359", "passId": 7 },
    "internal/bot/admin.go":      { "hash": "f053c8fe5baabc6351fa40a95c29e6ccbc7c1ae2", "coverage": "full", "reason": null, "lines": 322, "lastReadSHA": "eb19359", "passId": 8 },
    "internal/bot/markup.go":     { "hash": "ada20dcd964c091b743e55f45c3b4e8ed371b84a", "coverage": "full", "reason": null, "lines": 131, "lastReadSHA": "eb19359", "passId": 8 },
    "internal/config/config.go":  { "hash": "9dfee0f73539c7b356cb15fbccd176bbae1079a7", "coverage": "full", "reason": null, "lines": 258, "lastReadSHA": "eb19359", "passId": 8 },
    "internal/encoder/encoder.go":{ "hash": "bb1c4573d98ad4121e22c3c593e1c0d20b599f37", "coverage": "full", "reason": null, "lines": 183, "lastReadSHA": "eb19359", "passId": 9 },
    "internal/health/health.go":  { "hash": "b8ea3be7533961ebc61e249d5f815a4e83371426", "coverage": "full", "reason": null, "lines": 40,  "lastReadSHA": "eb19359", "passId": 9 },
    "internal/texts/texts.go":    { "hash": "b551031e7c247f613cea5b71c6c0116af73a727a", "coverage": "full", "reason": null, "lines": 48,  "lastReadSHA": "eb19359", "passId": 9 },
    "internal/bot/texts_inline.go":  { "hash": "d6450bab736c2d387574f9c07a75b3fed1b03133", "coverage": "full", "reason": null, "lines": 95, "lastReadSHA": "eb19359", "passId": 9 },
    "internal/bot/texts_settings.go":{ "hash": "89916927f5045be51edf13bfbeba93a670bb3a5e", "coverage": "full", "reason": null, "lines": 42, "lastReadSHA": "eb19359", "passId": 9 },
    "internal/db/db_test.go":        { "hash": "6fab9de91f88d83b34544ad2a47a82ce34542c2b", "coverage": "full", "reason": null, "lines": 372, "lastReadSHA": "eb19359", "passId": 3 },
    "internal/encoder/encoder_test.go": { "hash": "a96dc0caa210af0ed23fc0568421b36057f30423", "coverage": "full", "reason": null, "lines": 125, "lastReadSHA": "eb19359", "passId": 9 }
  },
  "themes": {
    "concurrency":      ["F-0001","F-0002","F-0003","F-0004"],
    "resource-leak":    ["F-0005"],
    "error-handling":   ["F-0006","F-0007","F-0008"],
    "test-coverage":    ["F-0009","F-0010"],
    "input-validation": ["F-0011"],
    "edge":             ["F-0012","F-0013"],
    "perf":             ["F-0014"]
  },
  "passes": { "total": 9, "completed": 9, "cursor": null }
}
